{"data":{"markdownRemark":{"html":"<h3>Failed downloads:</h3>\n<h3>Failed hexagons:</h3>\n<h3>Hexagons images:</h3>\n<p> <img src=\"/wes.jpg_hexagon-73aafbc44949a56b6135bbd581f5322d.jpeg\" alt=\"wes.jpg_hexagon.jpeg\"></p>","frontmatter":{"path":"/wesley_willis_images","title":"Wesley Willis (images)","date":"2001-10-10","tags":["news"]}}},"pageContext":{"isCreatedByStatefulCreatePages":false,"prev":{"html":"<p><img src=\"/visit_nunavut-ce98503fedf9c2623ff8c0ce6970c8d8.jpg\" alt=\"Visit Nunavut\">  </p>","id":"380048e7-5c9c-510c-b2bb-af82f6b42fb1","frontmatter":{"path":"/visit_nunavut","title":"Visit Nunavut","date":"2010-06-17","tags":["beadwork"],"hexagonImages":["visit_nunavut.jpeg_hexagon.jpeg","visit_nunavut.jpg_hexagon.jpeg"]}},"next":{"html":"<p>I met Wes on the plane to Munich. </p>\n<p><img src=\"/wes-dad943d9099729577f0d0d8b85e4d422.jpg\" alt=\"Wesley Freaking Willis\"></p>","id":"0196ba31-721c-5e0b-b863-66c44a916aff","frontmatter":{"path":"/wesley_willis","title":"Wesley Willis","date":"2001-10-10","tags":["news"],"hexagonImages":["wes.jpg_hexagon.jpeg"]}}}}